Workbook

Sheet Start_Here
A1: ExperimentLab | Conversion & A/B Testing
A2: Excel + statistical reasoning. Every statistic in this workbook is a live formula driven by the Inputs sheet.
A4: Business question | B4: Does the advertising treatment increase conversion enough to justify continued investment?
A5: Dataset | B5: Marketing A/B Testing dataset: 588,101 users, ad group vs PSA comparison group (data/marketing_ab_clean.csv in the repo; reproduced with formulas in ExperimentLab_Verification.xlsx).
A6: Headline result | B6: =TEXT(Summary!B7,"0.000%")&" (ad) vs "&TEXT(Summary!C7,"0.000%")&" (PSA): +"&TEXT(Summary!B8*100,"0.000")&" pp absolute, "&TEXT(Summary!B9,"0.0%")&" relative lift." -> 2.555% (ad) vs 1.785% (PSA): +0.769 pp absolute, 43.1% relative lift.
A7: Statistical result | B7: ="z = "&TEXT(Statistical_Test!B11,"0.000")&", two-sided p = "&TEXT(Statistical_Test!B12,"0.00E+00")&", 95% CI for difference = ["&TEXT(Statistical_Test!B15*100,"0.000")&", "&TEXT(Statistical_Test!B16*100,"0.000")&"] pp." -> z = 7.370, two-sided p = 1.71E-13, 95% CI for difference = [0.595, 0.943] pp.
A8: Key insight | B8: ="The lift is concentrated in heavily-exposed users: those who saw 21+ ads account for "&TEXT(Segment_Frequency!B27,"0%")&" of band-level incremental conversions ("&TEXT(Segment_Frequency!B28,"0%")&" from 51+). Below 21 ads there is no significant difference. Exposure profiles also differ between groups (Balance_Check), so verify assignment." -> The lift is concentrated in heavily-exposed users: those who saw 21+ ads account for 104% of band-level incremental conversions (83% from 51+). Below 21 ads there is no significant difference. Exposure profiles also differ between groups (Balance_Check), so verify assignment.
A9: Business implication | B9: Break_Even shows what each incremental conversion must be worth for the ad spend to pay back. Spend and conversion value are NOT in the dataset, so those inputs are illustrative placeholders.
A10: Important limitation | B10: The dataset does not document how users were assigned to groups. Treat the result as an association unless randomization is verified.
A12: Sheet guide
A13: Inputs | B13: Every hardcoded number (blue font), with its source. Change nothing else by hand.
A14: Data_Quality | B14: Validation checks on the source CSV and reconciliation of workbook tables to the group totals.
A15: Summary | B15: Conversion rates, absolute difference, relative lift, effect size, incremental conversions.
A16: Statistical_Test | B16: Two-proportion z-test, confidence intervals (difference and relative lift), minimum detectable effect, power.
A17: Break_Even | B17: Illustrative ROI: break-even value per conversion and a profit sensitivity grid. Yellow cells are assumptions to replace.
A18: Segment_Day / Segment_Frequency | B18: Exploratory segment tests with Bonferroni-adjusted p-values; frequency-standardised (Mantel-Haenszel) difference.
A19: Balance_Check | B19: Do the two groups have a similar exposure profile? (chi-square tests)
A20: Power_Planner | B20: Independent chi-square cross-check of the headline test, and the sample size a follow-up experiment needs.
A21: Charts | B21: Native Excel charts.
A22: Decision_Memo | B22: Stakeholder recommendation, driven by the numbers above.
A23: Verification workbook | B23: Separate workbook holding the raw 588,101 rows; COUNTIFS / SUMIFS recompute every input on this sheet and flag any mismatch.
A25: Colour legend | B25: Blue font = hardcoded input | Black = formula | Green = link to another sheet | Yellow fill = assumption you should replace

Sheet Inputs
A1: Inputs
A2: All hardcoded values live here. Source: data/marketing_ab_clean.csv. Counts are reproduced with COUNTIFS / SUMIFS in workbook/ExperimentLab_Verification.xlsx (or with a PivotTable).
A3: Parameter | B3: Value | C3: Source / note
A4: Ad group users | B4: 564577 | C4: COUNTIF(test_group = "ad")
A5: Ad group conversions | B5: 14423 | C5: SUMIFS(converted, test_group = "ad")
A6: PSA group users | B6: 23524 | C6: COUNTIF(test_group = "psa")
A7: PSA group conversions | B7: 420 | C7: SUMIFS(converted, test_group = "psa")
A8: Ad-group ad impressions | B8: 14014701 | C8: SUMIFS(total_ads, test_group = "ad")
A9: PSA-group ad impressions | B9: 582481 | C9: SUMIFS(total_ads, test_group = "psa")
A10: Significance level (alpha) | B10: 0.05 | C10: Analyst choice, two-sided
A11: Confidence level | B11: =1-B10 -> 0.95 | C11: Formula: 1 - alpha
A12: Target statistical power | B12: 0.8 | C12: Analyst choice, used for minimum detectable effect
A13: Mean ads per user: ad group | B13: 24.8234 | C13: AVERAGEIFS(total_ads, test_group = "ad")
A14: Mean ads per user: PSA group | B14: 24.7611 | C14: AVERAGEIFS(total_ads, test_group = "psa")
A15: Median ads per user: ad group | B15: 13 | C15: Median of total_ads, ad group
A16: Median ads per user: PSA group | B16: 12 | C16: Median of total_ads, PSA group

Sheet Data_Quality
A1: Data quality
A2: Checks run on data/marketing_ab_clean.csv (reproduced live with formulas in workbook/ExperimentLab_Verification.xlsx), plus live reconciliation of this workbook to the group totals.
A4: Check | B4: Result | C4: Expected | D4: Status
A5: Rows | B5: 588101 | D5: =IF(C5="","info",IF(B5=C5,"OK","CHECK")) -> info
A6: Unique user IDs | B6: 588101 | C6: 588101 | D6: =IF(C6="","info",IF(B6=C6,"OK","CHECK")) -> OK
A7: Duplicate user IDs | B7: 0 | C7: 0 | D7: =IF(C7="","info",IF(B7=C7,"OK","CHECK")) -> OK
A8: Missing cells | B8: 0 | C8: 0 | D8: =IF(C8="","info",IF(B8=C8,"OK","CHECK")) -> OK
A9: Unexpected group labels | B9: 0 | C9: 0 | D9: =IF(C9="","info",IF(B9=C9,"OK","CHECK")) -> OK
A10: Invalid conversion values (not 0/1) | B10: 0 | C10: 0 | D10: =IF(C10="","info",IF(B10=C10,"OK","CHECK")) -> OK
A11: Negative total_ads | B11: 0 | C11: 0 | D11: =IF(C11="","info",IF(B11=C11,"OK","CHECK")) -> OK
A12: Users with total_ads = 0 | B12: 0 | C12: 0 | D12: =IF(C12="","info",IF(B12=C12,"OK","CHECK")) -> OK
A13: Invalid hour values (not 0-23) | B13: 0 | C13: 0 | D13: =IF(C13="","info",IF(B13=C13,"OK","CHECK")) -> OK
A14: Invalid weekday labels | B14: 0 | C14: 0 | D14: =IF(C14="","info",IF(B14=C14,"OK","CHECK")) -> OK
A16: Reconciliation (live formulas)
A17: Ad + PSA users = rows | B17: =Inputs!B4+Inputs!B6 -> 588101 | C17: =B5 -> 588101 | D17: =IF(B17=C17,"OK","CHECK") -> OK
A18: Day table users (ad) = ad users | B18: =Segment_Day!B13 -> 564577 | C18: =Inputs!B4 -> 564577 | D18: =IF(B18=C18,"OK","CHECK") -> OK
A19: Day table users (PSA) = PSA users | B19: =Segment_Day!D13 -> 23524 | C19: =Inputs!B6 -> 23524 | D19: =IF(B19=C19,"OK","CHECK") -> OK
A20: Day table conversions (ad + PSA) | B20: =Segment_Day!C13+Segment_Day!E13 -> 14843 | C20: =Inputs!B5+Inputs!B7 -> 14843 | D20: =IF(B20=C20,"OK","CHECK") -> OK
A21: Frequency table users (ad) = ad users | B21: =Segment_Frequency!B13 -> 564577 | C21: =Inputs!B4 -> 564577 | D21: =IF(B21=C21,"OK","CHECK") -> OK
A22: Frequency table users (PSA) = PSA users | B22: =Segment_Frequency!D13 -> 23524 | C22: =Inputs!B6 -> 23524 | D22: =IF(B22=C22,"OK","CHECK") -> OK
A23: Frequency table conversions (ad + PSA) | B23: =Segment_Frequency!C13+Segment_Frequency!E13 -> 14843 | C23: =Inputs!B5+Inputs!B7 -> 14843 | D23: =IF(B23=C23,"OK","CHECK") -> OK
A25: Rows removed: 0. Only the index-like "Unnamed: 0" column was dropped when the CSV was cleaned. User IDs span 900,000 to 1,654,483.

Sheet Summary
A1: Summary
A2: Ad (test) vs PSA (comparison)
A4: Metric | B4: Ad (test) | C4: PSA (comparison) | D4: Definition
A5: Users | B5: =Inputs!B4 -> 564577 | C5: =Inputs!B6 -> 23524 | D5: Records per group
A6: Conversions | B6: =Inputs!B5 -> 14423 | C6: =Inputs!B7 -> 420 | D6: Count with converted = 1
A7: Conversion rate | B7: =B6/B5 -> 0.02554656 | C7: =C6/C5 -> 0.017854106 | D7: Conversions / users
A8: Absolute difference (Ad - PSA) | B8: =B7-C7 -> 0.0076924532 | D8: Difference in proportions (percentage points)
A9: Relative lift vs PSA | B9: =B8/C7 -> 0.43085064 | D9: Absolute difference / PSA rate
A10: Share of all users | B10: =B5/(B5+C5) -> 0.96000007 | C10: =C5/(B5+C5) -> 0.039999932 | D10: Group users / total users
A11: Cohen's h | B11: =2*(ASIN(SQRT(B7))-ASIN(SQRT(C7))) -> 0.053002579 | D11: Effect size for proportions (0.2 small, 0.5 medium)
A12: Incremental conversions (if causal) | B12: =B8*B5 -> 4342.9821 | D12: Absolute difference x ad-group users
A13: Share of ad conversions that are incremental | B13: =B12/B6 -> 0.30111503 | D13: Incremental / observed ad-group conversions
A14: Incremental conversions per 1,000 ad users | B14: =B8*1000 -> 7.6924532 | D14: Absolute difference x 1,000
A16: Note: "incremental" figures are only causal if group assignment was random. See Decision_Memo.

Sheet Statistical_Test
A1: Statistical test
A2: Two-proportion z-test (pooled SE) and confidence intervals (unpooled SE). Large-sample normal approximation.
A4: Metric | B4: Value | C4: Interpretation
A5: Null hypothesis | B5: p_ad = p_psa | C5: Two-sided test
A6: Alternative hypothesis | B6: p_ad <> p_psa | C6: Any difference
A7: p_ad | B7: =Summary!B7 -> 0.02554656 | C7: Ad conversion rate
A8: p_psa | B8: =Summary!C7 -> 0.017854106 | C8: PSA conversion rate
A9: Pooled conversion rate | B9: =(Inputs!B5+Inputs!B7)/(Inputs!B4+Inputs!B6) -> 0.025238862 | C9: Used for the z-test standard error
A10: Pooled standard error | B10: =SQRT(B9*(1-B9)*(1/Inputs!B4+1/Inputs!B6)) -> 0.0010437411 | C10: SQRT(p(1-p)(1/n1+1/n2))
A11: Z statistic | B11: =(B7-B8)/B10 -> 7.3700781 | C11: Observed difference / pooled SE
A12: Two-sided p-value | B12: =2*NORMSDIST(-ABS(B11)) -> 1.7052807e-13 | C12: Probability of a difference this large if p_ad = p_psa
A13: Critical z | B13: =NORMSINV(1-Inputs!B10/2) -> 1.959964 | C13: From alpha on Inputs
A14: Unpooled standard error | B14: =SQRT(B7*(1-B7)/Inputs!B4+B8*(1-B8)/Inputs!B6) -> 0.00088854733 | C14: Used for the confidence interval
A15: CI lower bound (difference) | B15: =(B7-B8)-B13*B14 -> 0.0059509324 | C15: Lower bound for Ad - PSA
A16: CI upper bound (difference) | B16: =(B7-B8)+B13*B14 -> 0.009433974 | C16: Upper bound for Ad - PSA
A17: Risk ratio (Ad / PSA) | B17: =B7/B8 -> 1.4308506 | C17: Relative conversion
A18: SE of ln(risk ratio) | B18: =SQRT((1-B7)/Inputs!B5+(1-B8)/Inputs!B7) -> 0.049051046 | C18: Delta method
A19: CI lower bound (relative lift) | B19: =EXP(LN(B17)-B13*B18)-1 -> 0.29969658 | C19: Relative lift = risk ratio - 1
A20: CI upper bound (relative lift) | B20: =EXP(LN(B17)+B13*B18)-1 -> 0.57523962 | C20: Relative lift = risk ratio - 1
A21: Conclusion | B21: =IF(B12<Inputs!B10,"Statistically significant at "&TEXT(Inputs!B10,"0%"),"Not statistically significant at "&TEXT(Inputs!B10,"0%")) -> Statistically significant at 5% | C21: Statistical significance does not imply profitability
A22: Minimum detectable effect (abs.) | B22: =(B13+NORMSINV(Inputs!B12))*B10 -> 0.0029241295 | C22: Smallest difference detectable at the target power with these group sizes
A23: Approximate power at observed effect | B23: =NORMSDIST(ABS(B7-B8)/B14-B13) -> 1 | C23: Retrospective; shown for completeness
A24: Practical impact | B24: See Break_Even | C24: Spend and conversion value are not in the dataset

Sheet Break_Even
A1: Break-even analysis (ILLUSTRATIVE)
A2: The dataset has no spend or conversion value. Yellow cells are placeholder assumptions: replace them with real figures.
A3: Assumes the ad group is billed for its ad impressions and the comparison group is not (holdout). If PSA impressions were also purchased, incremental cost is lower. Treat output as a framework, not a result.
A5: Assumption | B5: Value | C5: Note
A6: Cost per 1,000 ad impressions (CPM, $) | B6: 5 | C6: Placeholder
A7: Value (margin) per conversion ($) | B7: 25 | C7: Placeholder
A9: Calculation | B9: Point estimate | C9: CI lower | D9: CI upper
A10: Ad impressions served (ad group) | B10: =Inputs!$B$8 -> 14014701 | C10: =Inputs!$B$8 -> 14014701 | D10: =Inputs!$B$8 -> 14014701
A11: Campaign cost ($) | B11: =B10/1000*$B$6 -> 70073.505 | C11: =C10/1000*$B$6 -> 70073.505 | D11: =D10/1000*$B$6 -> 70073.505
A12: Incremental conversions | B12: =Summary!B12 -> 4342.9821 | C12: =Statistical_Test!B15*Inputs!B4 -> 3359.7596 | D12: =Statistical_Test!B16*Inputs!B4 -> 5326.2047
A13: Cost per incremental conversion ($) | B13: =IF(B12>0,B11/B12,"n/a") -> 16.134882 | C13: =IF(C12>0,C11/C12,"n/a") -> 20.856702 | D13: =IF(D12>0,D11/D12,"n/a") -> 13.156367
A14: BREAK-EVEN value per conversion ($) | B14: =B13 -> 16.134882 | C14: =C13 -> 20.856702 | D14: =D13 -> 13.156367
A15: Incremental revenue at assumed value ($) | B15: =B12*$B$7 -> 108574.55 | C15: =C12*$B$7 -> 83993.989 | D15: =D12*$B$7 -> 133155.12
A16: Net profit ($) | B16: =B15-B11 -> 38501.049 | C16: =C15-C11 -> 13920.484 | D16: =D15-D11 -> 63081.613
A17: ROI | B17: =B16/B11 -> 0.54943803 | C17: =C16/C11 -> 0.19865546 | D17: =D16/D11 -> 0.9002206
A18: Reading the table: the CI columns reuse the confidence interval of the conversion-rate difference, so they show how the economics change across the statistical uncertainty alone.
A20: Net profit sensitivity (point estimate): rows = CPM ($), columns = value per conversion ($)
A21: CPM \ Value | B21: 5 | C21: 10 | D21: 25 | E21: 50 | F21: 100 | G21: 250
A22: 1 | B22: =Summary!$B$12*B$21-Inputs!$B$8/1000*$A22 -> 7700.2097 | C22: =Summary!$B$12*C$21-Inputs!$B$8/1000*$A22 -> 29415.12 | D22: =Summary!$B$12*D$21-Inputs!$B$8/1000*$A22 -> 94559.853 | E22: =Summary!$B$12*E$21-Inputs!$B$8/1000*$A22 -> 203134.41 | F22: =Summary!$B$12*F$21-Inputs!$B$8/1000*$A22 -> 420283.51 | G22: =Summary!$B$12*G$21-Inputs!$B$8/1000*$A22 -> 1071730.8
A23: 2 | B23: =Summary!$B$12*B$21-Inputs!$B$8/1000*$A23 -> -6314.4913 | C23: =Summary!$B$12*C$21-Inputs!$B$8/1000*$A23 -> 15400.419 | D23: =Summary!$B$12*D$21-Inputs!$B$8/1000*$A23 -> 80545.152 | E23: =Summary!$B$12*E$21-Inputs!$B$8/1000*$A23 -> 189119.71 | F23: =Summary!$B$12*F$21-Inputs!$B$8/1000*$A23 -> 406268.81 | G23: =Summary!$B$12*G$21-Inputs!$B$8/1000*$A23 -> 1057716.1
A24: 5 | B24: =Summary!$B$12*B$21-Inputs!$B$8/1000*$A24 -> -48358.594 | C24: =Summary!$B$12*C$21-Inputs!$B$8/1000*$A24 -> -26643.684 | D24: =Summary!$B$12*D$21-Inputs!$B$8/1000*$A24 -> 38501.049 | E24: =Summary!$B$12*E$21-Inputs!$B$8/1000*$A24 -> 147075.6 | F24: =Summary!$B$12*F$21-Inputs!$B$8/1000*$A24 -> 364224.71 | G24: =Summary!$B$12*G$21-Inputs!$B$8/1000*$A24 -> 1015672
A25: 10 | B25: =Summary!$B$12*B$21-Inputs!$B$8/1000*$A25 -> -118432.1 | C25: =Summary!$B$12*C$21-Inputs!$B$8/1000*$A25 -> -96717.189 | D25: =Summary!$B$12*D$21-Inputs!$B$8/1000*$A25 -> -31572.456 | E25: =Summary!$B$12*E$21-Inputs!$B$8/1000*$A25 -> 77002.097 | F25: =Summary!$B$12*F$21-Inputs!$B$8/1000*$A25 -> 294151.2 | G25: =Summary!$B$12*G$21-Inputs!$B$8/1000*$A25 -> 945598.53
A26: 20 | B26: =Summary!$B$12*B$21-Inputs!$B$8/1000*$A26 -> -258579.11 | C26: =Summary!$B$12*C$21-Inputs!$B$8/1000*$A26 -> -236864.2 | D26: =Summary!$B$12*D$21-Inputs!$B$8/1000*$A26 -> -171719.47 | E26: =Summary!$B$12*E$21-Inputs!$B$8/1000*$A26 -> -63144.913 | F26: =Summary!$B$12*F$21-Inputs!$B$8/1000*$A26 -> 154004.19 | G26: =Summary!$B$12*G$21-Inputs!$B$8/1000*$A26 -> 805451.52
A27: 40 | B27: =Summary!$B$12*B$21-Inputs!$B$8/1000*$A27 -> -538873.13 | C27: =Summary!$B$12*C$21-Inputs!$B$8/1000*$A27 -> -517158.22 | D27: =Summary!$B$12*D$21-Inputs!$B$8/1000*$A27 -> -452013.49 | E27: =Summary!$B$12*E$21-Inputs!$B$8/1000*$A27 -> -343438.93 | F27: =Summary!$B$12*F$21-Inputs!$B$8/1000*$A27 -> -126289.83 | G27: =Summary!$B$12*G$21-Inputs!$B$8/1000*$A27 -> 525157.5
A29: Green = campaign pays back at that CPM and conversion value; red = it does not. Axis values (blue) can be edited.

Sheet Segment_Day
A1: Segment Day
A2: Conversion by weekday on which the user saw the most ads
A5: Day with most ads | B5: Ad users | C5: Ad conv. | D5: PSA users | E5: PSA conv. | F5: Ad rate | G5: PSA rate | H5: Difference | I5: SE (unpooled) | J5: CI lower | K5: CI upper | L5: z | M5: p (raw) | N5: p (Bonferroni) | O5: Sig. after correction? | P5: Incremental conv. | Q5: Share of incremental
A6: Monday | B6: 83571 | C6: 2778 | D6: 3502 | E6: 79 | F6: =C6/B6 -> 0.033241196 | G6: =E6/D6 -> 0.022558538 | H6: =F6-G6 -> 0.010682658 | I6: =SQRT(F6*(1-F6)/B6+G6*(1-G6)/D6) -> 0.0025847321 | J6: =H6-Statistical_Test!$B$13*I6 -> 0.0056166763 | K6: =H6+Statistical_Test!$B$13*I6 -> 0.01574864 | L6: =H6/SQRT(((C6+E6)/(B6+D6))*(1-(C6+E6)/(B6+D6))*(1/B6+1/D6)) -> 3.4765984 | M6: =2*NORMSDIST(-ABS(L6)) -> 0.00050781779 | N6: =MIN(1,M6*COUNT($M$6:$M$12)) -> 0.0035547246 | O6: =IF(N6<Inputs!$B$10,"Yes","No") -> Yes | P6: =H6*B6 -> 892.76042 | Q6: =P6/$P$13 -> 0.20316649
A7: Tuesday | B7: 74572 | C7: 2270 | D7: 2907 | E7: 42 | F7: =C7/B7 -> 0.03044038 | G7: =E7/D7 -> 0.014447884 | H7: =F7-G7 -> 0.015992495 | I7: =SQRT(F7*(1-F7)/B7+G7*(1-G7)/D7) -> 0.0023008697 | J7: =H7-Statistical_Test!$B$13*I7 -> 0.011482874 | K7: =H7+Statistical_Test!$B$13*I7 -> 0.020502117 | L7: =H7/SQRT(((C7+E7)/(B7+D7))*(1-(C7+E7)/(B7+D7))*(1/B7+1/D7)) -> 4.9717711 | M7: =2*NORMSDIST(-ABS(L7)) -> 6.6344014e-07 | N7: =MIN(1,M7*COUNT($M$6:$M$12)) -> 4.644081e-06 | O7: =IF(N7<Inputs!$B$10,"Yes","No") -> Yes | P7: =H7*B7 -> 1192.5924 | Q7: =P7/$P$13 -> 0.27139958
A8: Wednesday | B8: 77418 | C8: 1963 | D8: 3490 | E8: 55 | F8: =C8/B8 -> 0.02535586 | G8: =E8/D8 -> 0.015759312 | H8: =F8-G8 -> 0.0095965481 | I8: =SQRT(F8*(1-F8)/B8+G8*(1-G8)/D8) -> 0.0021825706 | J8: =H8-Statistical_Test!$B$13*I8 -> 0.0053187883 | K8: =H8+Statistical_Test!$B$13*I8 -> 0.013874308 | L8: =H8/SQRT(((C8+E8)/(B8+D8))*(1-(C8+E8)/(B8+D8))*(1/B8+1/D8)) -> 3.5560913 | M8: =2*NORMSDIST(-ABS(L8)) -> 0.00037641329 | N8: =MIN(1,M8*COUNT($M$6:$M$12)) -> 0.002634893 | O8: =IF(N8<Inputs!$B$10,"Yes","No") -> Yes | P8: =H8*B8 -> 742.94556 | Q8: =P8/$P$13 -> 0.16907296
A9: Thursday | B9: 79077 | C9: 1711 | D9: 3905 | E9: 79 | F9: =C9/B9 -> 0.021637138 | G9: =E9/D9 -> 0.020230474 | H9: =F9-G9 -> 0.0014066647 | I9: =SQRT(F9*(1-F9)/B9+G9*(1-G9)/D9) -> 0.0023116126 | J9: =H9-Statistical_Test!$B$13*I9 -> -0.0031240126 | K9: =H9+Statistical_Test!$B$13*I9 -> 0.0059373421 | L9: =H9/SQRT(((C9+E9)/(B9+D9))*(1-(C9+E9)/(B9+D9))*(1/B9+1/D9)) -> 0.59065655 | M9: =2*NORMSDIST(-ABS(L9)) -> 0.55475057 | N9: =MIN(1,M9*COUNT($M$6:$M$12)) -> 1 | O9: =IF(N9<Inputs!$B$10,"Yes","No") -> No | P9: =H9*B9 -> 111.23483 | Q9: =P9/$P$13 -> 0.025313835
A10: Friday | B10: 88805 | C10: 1995 | D10: 3803 | E10: 62 | F10: =C10/B10 -> 0.022464951 | G10: =E10/D10 -> 0.016302919 | H10: =F10-G10 -> 0.0061620325 | I10: =SQRT(F10*(1-F10)/B10+G10*(1-G10)/D10) -> 0.0021128785 | J10: =H10-Statistical_Test!$B$13*I10 -> 0.0020208668 | K10: =H10+Statistical_Test!$B$13*I10 -> 0.010303198 | L10: =H10/SQRT(((C10+E10)/(B10+D10))*(1-(C10+E10)/(B10+D10))*(1/B10+1/D10)) -> 2.5250288 | M10: =2*NORMSDIST(-ABS(L10)) -> 0.01156888 | N10: =MIN(1,M10*COUNT($M$6:$M$12)) -> 0.080982158 | O10: =IF(N10<Inputs!$B$10,"Yes","No") -> No | P10: =H10*B10 -> 547.2193 | Q10: =P10/$P$13 -> 0.12453131
A11: Saturday | B11: 78802 | C11: 1679 | D11: 2858 | E11: 40 | F11: =C11/B11 -> 0.021306566 | G11: =E11/D11 -> 0.013995801 | H11: =F11-G11 -> 0.0073107646 | I11: =SQRT(F11*(1-F11)/B11+G11*(1-G11)/D11) -> 0.0022567993 | J11: =H11-Statistical_Test!$B$13*I11 -> 0.0028875192 | K11: =H11+Statistical_Test!$B$13*I11 -> 0.01173401 | L11: =H11/SQRT(((C11+E11)/(B11+D11))*(1-(C11+E11)/(B11+D11))*(1/B11+1/D11)) -> 2.6745116 | M11: =2*NORMSDIST(-ABS(L11)) -> 0.0074838179 | N11: =MIN(1,M11*COUNT($M$6:$M$12)) -> 0.052386726 | O11: =IF(N11<Inputs!$B$10,"Yes","No") -> No | P11: =H11*B11 -> 576.10287 | Q11: =P11/$P$13 -> 0.13110438
A12: Sunday | B12: 82332 | C12: 2027 | D12: 3059 | E12: 63 | F12: =C12/B12 -> 0.024619832 | G12: =E12/D12 -> 0.020594966 | H12: =F12-G12 -> 0.0040248662 | I12: =SQRT(F12*(1-F12)/B12+G12*(1-G12)/D12) -> 0.0026240413 | J12: =H12-Statistical_Test!$B$13*I12 -> -0.0011181603 | K12: =H12+Statistical_Test!$B$13*I12 -> 0.0091678927 | L12: =H12/SQRT(((C12+E12)/(B12+D12))*(1-(C12+E12)/(B12+D12))*(1/B12+1/D12)) -> 1.4145989 | M12: =2*NORMSDIST(-ABS(L12)) -> 0.15718613 | N12: =MIN(1,M12*COUNT($M$6:$M$12)) -> 1 | O12: =IF(N12<Inputs!$B$10,"Yes","No") -> No | P12: =H12*B12 -> 331.37529 | Q12: =P12/$P$13 -> 0.075411446
A13: All users | B13: =SUM(B6:B12) -> 564577 | C13: =SUM(C6:C12) -> 14423 | D13: =SUM(D6:D12) -> 23524 | E13: =SUM(E6:E12) -> 420 | F13: =C13/B13 -> 0.02554656 | G13: =E13/D13 -> 0.017854106 | H13: =F13-G13 -> 0.0076924532 | I13: =SQRT(F13*(1-F13)/B13+G13*(1-G13)/D13) -> 0.00088854733 | J13: =H13-Statistical_Test!$B$13*I13 -> 0.0059509324 | K13: =H13+Statistical_Test!$B$13*I13 -> 0.009433974 | P13: =SUM(P6:P12) -> 4394.2306 | Q13: =SUM(Q6:Q12) -> 1
A15: Exploratory. Bonferroni multiplies each raw p-value by the number of tests in this table (capped at 1). Segments are defined by post-exposure behaviour, so they describe who responds; they are not randomised subgroups.

Sheet Segment_Frequency
A1: Segment Frequency
A2: Conversion by total ads seen (frequency band)
A5: Ads seen (band) | B5: Ad users | C5: Ad conv. | D5: PSA users | E5: PSA conv. | F5: Ad rate | G5: PSA rate | H5: Difference | I5: SE (unpooled) | J5: CI lower | K5: CI upper | L5: z | M5: p (raw) | N5: p (Bonferroni) | O5: Sig. after correction? | P5: Incremental conv. | Q5: Share of incremental | S5: MH weight | T5: MH numerator | U5: MH variance term
A6: 1 | B6: 54298 | C6: 86 | D6: 2308 | E6: 3 | F6: =C6/B6 -> 0.0015838521 | G6: =E6/D6 -> 0.0012998267 | H6: =F6-G6 -> 0.00028402539 | I6: =SQRT(F6*(1-F6)/B6+G6*(1-G6)/D6) -> 0.00076913882 | J6: =H6-Statistical_Test!$B$13*I6 -> -0.001223459 | K6: =H6+Statistical_Test!$B$13*I6 -> 0.0017915098 | L6: =H6/SQRT(((C6+E6)/(B6+D6))*(1-(C6+E6)/(B6+D6))*(1/B6+1/D6)) -> 0.33729792 | M6: =2*NORMSDIST(-ABS(L6)) -> 0.73589233 | N6: =MIN(1,M6*COUNT($M$6:$M$12)) -> 1 | O6: =IF(N6<Inputs!$B$10,"Yes","No") -> No | P6: =H6*B6 -> 15.42201 | Q6: =P6/$P$13 -> 0.0034217369 | S6: =B6*D6/(B6+D6) -> 2213.8958 | T6: =(C6*D6-E6*B6)/(B6+D6) -> 0.6288026 | U6: =(C6*(B6-C6)*D6^3+E6*(D6-E6)*B6^3)/(B6*D6*(B6+D6)^2) -> 2.8995046
A7: 2-5 | B7: 115664 | C7: 341 | D7: 5553 | E7: 19 | F7: =C7/B7 -> 0.0029481948 | G7: =E7/D7 -> 0.0034215739 | H7: =F7-G7 -> -0.00047337915 | I7: =SQRT(F7*(1-F7)/B7+G7*(1-G7)/D7) -> 0.00079967033 | J7: =H7-Statistical_Test!$B$13*I7 -> -0.0020407042 | K7: =H7+Statistical_Test!$B$13*I7 -> 0.0010939459 | L7: =H7/SQRT(((C7+E7)/(B7+D7))*(1-(C7+E7)/(B7+D7))*(1/B7+1/D7)) -> -0.63323758 | M7: =2*NORMSDIST(-ABS(L7)) -> 0.52657851 | N7: =MIN(1,M7*COUNT($M$6:$M$12)) -> 1 | O7: =IF(N7<Inputs!$B$10,"Yes","No") -> No | P7: =H7*B7 -> -54.752926 | Q7: =P7/$P$13 -> -0.012148229 | S7: =B7*D7/(B7+D7) -> 5298.6148 | T7: =(C7*D7-E7*B7)/(B7+D7) -> -2.5082538 | U7: =(C7*(B7-C7)*D7^3+E7*(D7-E7)*B7^3)/(B7*D7*(B7+D7)^2) -> 17.953398
A8: 6-10 | B8: 79537 | C8: 386 | D8: 3415 | E8: 23 | F8: =C8/B8 -> 0.0048530872 | G8: =E8/D8 -> 0.0067349927 | H8: =F8-G8 -> -0.0018819054 | I8: =SQRT(F8*(1-F8)/B8+G8*(1-G8)/D8) -> 0.0014211324 | J8: =H8-Statistical_Test!$B$13*I8 -> -0.0046672738 | K8: =H8+Statistical_Test!$B$13*I8 -> 0.00090346295 | L8: =H8/SQRT(((C8+E8)/(B8+D8))*(1-(C8+E8)/(B8+D8))*(1/B8+1/D8)) -> -1.537409 | M8: =2*NORMSDIST(-ABS(L8)) -> 0.12419319 | N8: =MIN(1,M8*COUNT($M$6:$M$12)) -> 0.86935236 | O8: =IF(N8<Inputs!$B$10,"Yes","No") -> No | P8: =H8*B8 -> -149.68111 | Q8: =P8/$P$13 -> -0.033210287 | S8: =B8*D8/(B8+D8) -> 3274.41 | T8: =(C8*D8-E8*B8)/(B8+D8) -> -6.1621299 | U8: =(C8*(B8-C8)*D8^3+E8*(D8-E8)*B8^3)/(B8*D8*(B8+D8)^2) -> 21.653854
A9: 11-20 | B9: 123334 | C9: 1036 | D9: 4150 | E9: 34 | F9: =C9/B9 -> 0.0083999546 | G9: =E9/D9 -> 0.0081927711 | H9: =F9-G9 -> 0.00020718351 | I9: =SQRT(F9*(1-F9)/B9+G9*(1-G9)/D9) -> 0.0014232087 | J9: =H9-Statistical_Test!$B$13*I9 -> -0.0025822544 | K9: =H9+Statistical_Test!$B$13*I9 -> 0.0029966214 | L9: =H9/SQRT(((C9+E9)/(B9+D9))*(1-(C9+E9)/(B9+D9))*(1/B9+1/D9)) -> 0.14389941 | M9: =2*NORMSDIST(-ABS(L9)) -> 0.8855799 | N9: =MIN(1,M9*COUNT($M$6:$M$12)) -> 1 | O9: =IF(N9<Inputs!$B$10,"Yes","No") -> No | P9: =H9*B9 -> 25.552771 | Q9: =P9/$P$13 -> 0.0056694852 | S9: =B9*D9/(B9+D9) -> 4014.9046 | T9: =(C9*D9-E9*B9)/(B9+D9) -> 0.83182203 | U9: =(C9*(B9-C9)*D9^3+E9*(D9-E9)*B9^3)/(B9*D9*(B9+D9)^2) -> 32.650337
A10: 21-50 | B10: 125541 | C10: 3660 | D10: 5235 | E10: 114 | F10: =C10/B10 -> 0.029153822 | G10: =E10/D10 -> 0.021776504 | H10: =F10-G10 -> 0.007377318 | I10: =SQRT(F10*(1-F10)/B10+G10*(1-G10)/D10) -> 0.0020723562 | J10: =H10-Statistical_Test!$B$13*I10 -> 0.0033155744 | K10: =H10+Statistical_Test!$B$13*I10 -> 0.011439061 | L10: =H10/SQRT(((C10+E10)/(B10+D10))*(1-(C10+E10)/(B10+D10))*(1/B10+1/D10)) -> 3.1239742 | M10: =2*NORMSDIST(-ABS(L10)) -> 0.0017842612 | N10: =MIN(1,M10*COUNT($M$6:$M$12)) -> 0.012489829 | O10: =IF(N10<Inputs!$B$10,"Yes","No") -> Yes | P10: =H10*B10 -> 926.15587 | Q10: =P10/$P$13 -> 0.20548953 | S10: =B10*D10/(B10+D10) -> 5025.4415 | T10: =(C10*D10-E10*B10)/(B10+D10) -> 37.07428 | U10: =(C10*(B10-C10)*D10^3+E10*(D10-E10)*B10^3)/(B10*D10*(B10+D10)^2) -> 108.46191
A11: 51-100 | B11: 44149 | C11: 5135 | D11: 1853 | E11: 107 | F11: =C11/B11 -> 0.11631068 | G11: =E11/D11 -> 0.057744199 | H11: =F11-G11 -> 0.058566477 | I11: =SQRT(F11*(1-F11)/B11+G11*(1-G11)/D11) -> 0.0056294913 | J11: =H11-Statistical_Test!$B$13*I11 -> 0.047532876 | K11: =H11+Statistical_Test!$B$13*I11 -> 0.069600077 | L11: =H11/SQRT(((C11+E11)/(B11+D11))*(1-(C11+E11)/(B11+D11))*(1/B11+1/D11)) -> 7.772666 | M11: =2*NORMSDIST(-ABS(L11)) -> 7.6851218e-15 | N11: =MIN(1,M11*COUNT($M$6:$M$12)) -> 5.3795853e-14 | O11: =IF(N11<Inputs!$B$10,"Yes","No") -> Yes | P11: =H11*B11 -> 2585.6514 | Q11: =P11/$P$13 -> 0.57368777 | S11: =B11*D11/(B11+D11) -> 1778.3596 | T11: =(C11*D11-E11*B11)/(B11+D11) -> 104.15225 | U11: =(C11*(B11-C11)*D11^3+E11*(D11-E11)*B11^3)/(B11*D11*(B11+D11)^2) -> 100.22532
A12: 101+ | B12: 22054 | C12: 3779 | D12: 1010 | E12: 120 | F12: =C12/B12 -> 0.17135214 | G12: =E12/D12 -> 0.11881188 | H12: =F12-G12 -> 0.052540254 | I12: =SQRT(F12*(1-F12)/B12+G12*(1-G12)/D12) -> 0.010492728 | J12: =H12-Statistical_Test!$B$13*I12 -> 0.031974885 | K12: =H12+Statistical_Test!$B$13*I12 -> 0.073105624 | L12: =H12/SQRT(((C12+E12)/(B12+D12))*(1-(C12+E12)/(B12+D12))*(1/B12+1/D12)) -> 4.356451 | M12: =2*NORMSDIST(-ABS(L12)) -> 1.3218829e-05 | N12: =MIN(1,M12*COUNT($M$6:$M$12)) -> 9.2531806e-05 | O12: =IF(N12<Inputs!$B$10,"Yes","No") -> Yes | P12: =H12*B12 -> 1158.7228 | Q12: =P12/$P$13 -> 0.25708999 | S12: =B12*D12/(B12+D12) -> 965.7709 | T12: =(C12*D12-E12*B12)/(B12+D12) -> 50.741849 | U12: =(C12*(B12-C12)*D12^3+E12*(D12-E12)*B12^3)/(B12*D12*(B12+D12)^2) -> 102.68927
A13: All users | B13: =SUM(B6:B12) -> 564577 | C13: =SUM(C6:C12) -> 14423 | D13: =SUM(D6:D12) -> 23524 | E13: =SUM(E6:E12) -> 420 | F13: =C13/B13 -> 0.02554656 | G13: =E13/D13 -> 0.017854106 | H13: =F13-G13 -> 0.0076924532 | I13: =SQRT(F13*(1-F13)/B13+G13*(1-G13)/D13) -> 0.00088854733 | J13: =H13-Statistical_Test!$B$13*I13 -> 0.0059509324 | K13: =H13+Statistical_Test!$B$13*I13 -> 0.009433974 | P13: =SUM(P6:P12) -> 4507.0708 | Q13: =SUM(Q6:Q12) -> 1
A15: Exploratory. Bonferroni multiplies each raw p-value by the number of tests in this table (capped at 1). Segments are defined by post-exposure behaviour, so they describe who responds; they are not randomised subgroups.
A17: Frequency-standardised comparison (Mantel-Haenszel risk difference)
A18: Weighted average of the per-band differences, so any difference in how many ads each group saw cannot drive the result. Greenland-Robins variance.
A19: Metric | B19: Value
A20: MH risk difference (Ad - PSA) | B20: =SUM(T6:T12)/SUM(S6:S12) -> 0.0081855201
A21: Standard error | B21: =SQRT(SUM(U6:U12))/SUM(S6:S12) -> 0.00087103415
A22: CI lower | B22: =B20-Statistical_Test!B13*B21 -> 0.0064783245
A23: CI upper | B23: =B20+Statistical_Test!B13*B21 -> 0.0098927156
A24: Crude difference (unadjusted) | B24: =H13 -> 0.0076924532
A25: Adjusted - crude | B25: =B20-B24 -> 0.00049306686
A27: Share of incremental: 21+ ads | B27: =SUM(P10:P12)/P13 -> 1.0362673
A28: Share of incremental: 51+ ads | B28: =SUM(P11:P12)/P13 -> 0.83077776
A29: Band-level incremental conversions use each band's own PSA baseline, so their sum differs from the single overall figure on Summary. Shares can exceed 100% when other bands net negative.

Sheet Balance_Check
A1: Balance check
A2: Do the two groups have a similar exposure profile? Chi-square tests of independence (group x segment).
A4: Ads seen (band) | B4: Ad users | C4: PSA users | D4: Ad share | E4: PSA share | F4: Share diff (pp) | G4: Expected ad | H4: Expected PSA
A5: =Segment_Frequency!A6 -> 1 | B5: =Segment_Frequency!B6 -> 54298 | C5: =Segment_Frequency!D6 -> 2308 | D5: =B5/SUM($B$5:$B$11) -> 0.096174658 | E5: =C5/SUM($C$5:$C$11) -> 0.098112566 | F5: =(D5-E5)*100 -> -0.19379077 | G5: =(B5+C5)*SUM($B$5:$B$11)/(SUM($B$5:$B$11)+SUM($C$5:$C$11)) -> 54341.764 | H5: =(B5+C5)*SUM($C$5:$C$11)/(SUM($B$5:$B$11)+SUM($C$5:$C$11)) -> 2264.2361
A6: =Segment_Frequency!A7 -> 2-5 | B6: =Segment_Frequency!B7 -> 115664 | C6: =Segment_Frequency!D7 -> 5553 | D6: =B6/SUM($B$5:$B$11) -> 0.20486842 | E6: =C6/SUM($C$5:$C$11) -> 0.23605679 | F6: =(D6-E6)*100 -> -3.1188369 | G6: =(B6+C6)*SUM($B$5:$B$11)/(SUM($B$5:$B$11)+SUM($C$5:$C$11)) -> 116368.33 | H6: =(B6+C6)*SUM($C$5:$C$11)/(SUM($B$5:$B$11)+SUM($C$5:$C$11)) -> 4848.6718
A7: =Segment_Frequency!A8 -> 6-10 | B7: =Segment_Frequency!B8 -> 79537 | C7: =Segment_Frequency!D8 -> 3415 | D7: =B7/SUM($B$5:$B$11) -> 0.14087892 | E7: =C7/SUM($C$5:$C$11) -> 0.14517089 | F7: =(D7-E7)*100 -> -0.42919658 | G7: =(B7+C7)*SUM($B$5:$B$11)/(SUM($B$5:$B$11)+SUM($C$5:$C$11)) -> 79633.926 | H7: =(B7+C7)*SUM($C$5:$C$11)/(SUM($B$5:$B$11)+SUM($C$5:$C$11)) -> 3318.0744
A8: =Segment_Frequency!A9 -> 11-20 | B8: =Segment_Frequency!B9 -> 123334 | C8: =Segment_Frequency!D9 -> 4150 | D8: =B8/SUM($B$5:$B$11) -> 0.21845382 | E8: =C8/SUM($C$5:$C$11) -> 0.17641558 | F8: =(D8-E8)*100 -> 4.203824 | G8: =(B8+C8)*SUM($B$5:$B$11)/(SUM($B$5:$B$11)+SUM($C$5:$C$11)) -> 122384.65 | H8: =(B8+C8)*SUM($C$5:$C$11)/(SUM($B$5:$B$11)+SUM($C$5:$C$11)) -> 5099.3513
A9: =Segment_Frequency!A10 -> 21-50 | B9: =Segment_Frequency!B10 -> 125541 | C9: =Segment_Frequency!D10 -> 5235 | D9: =B9/SUM($B$5:$B$11) -> 0.22236294 | E9: =C9/SUM($C$5:$C$11) -> 0.22253868 | F9: =(D9-E9)*100 -> -0.017574669 | G9: =(B9+C9)*SUM($B$5:$B$11)/(SUM($B$5:$B$11)+SUM($C$5:$C$11)) -> 125544.97 | H9: =(B9+C9)*SUM($C$5:$C$11)/(SUM($B$5:$B$11)+SUM($C$5:$C$11)) -> 5231.0311
A10: =Segment_Frequency!A11 -> 51-100 | B10: =Segment_Frequency!B11 -> 44149 | C10: =Segment_Frequency!D11 -> 1853 | D10: =B10/SUM($B$5:$B$11) -> 0.078198368 | E10: =C10/SUM($C$5:$C$11) -> 0.078770617 | F10: =(D10-E10)*100 -> -0.057224926 | G10: =(B10+C10)*SUM($B$5:$B$11)/(SUM($B$5:$B$11)+SUM($C$5:$C$11)) -> 44161.923 | H10: =(B10+C10)*SUM($C$5:$C$11)/(SUM($B$5:$B$11)+SUM($C$5:$C$11)) -> 1840.0769
A11: =Segment_Frequency!A12 -> 101+ | B11: =Segment_Frequency!B12 -> 22054 | C11: =Segment_Frequency!D12 -> 1010 | D11: =B11/SUM($B$5:$B$11) -> 0.039062874 | E11: =C11/SUM($C$5:$C$11) -> 0.042934875 | F11: =(D11-E11)*100 -> -0.38720014 | G11: =(B11+C11)*SUM($B$5:$B$11)/(SUM($B$5:$B$11)+SUM($C$5:$C$11)) -> 22141.442 | H11: =(B11+C11)*SUM($C$5:$C$11)/(SUM($B$5:$B$11)+SUM($C$5:$C$11)) -> 922.55843
A12: Chi-square p-value | B12: =CHITEST(B5:C11,G5:H11) -> 1.6518385e-62 | C12: Max |share diff| (pp): | D12: =MAX(MAX(F5:F11),-MIN(F5:F11)) -> 4.203824 | E12: =IF(B12<Inputs!$B$10,"Distribution differs (check size of gap)","No evidence of imbalance") -> Distribution differs (check size of gap)
A15: Day with most ads | B15: Ad users | C15: PSA users | D15: Ad share | E15: PSA share | F15: Share diff (pp) | G15: Expected ad | H15: Expected PSA
A16: =Segment_Day!A6 -> Monday | B16: =Segment_Day!B6 -> 83571 | C16: =Segment_Day!D6 -> 3502 | D16: =B16/SUM($B$16:$B$22) -> 0.1480241 | E16: =C16/SUM($C$16:$C$22) -> 0.14886924 | F16: =(D16-E16)*100 -> -0.084514401 | G16: =(B16+C16)*SUM($B$16:$B$22)/(SUM($B$16:$B$22)+SUM($C$16:$C$22)) -> 83590.086 | H16: =(B16+C16)*SUM($C$16:$C$22)/(SUM($B$16:$B$22)+SUM($C$16:$C$22)) -> 3482.9141
A17: =Segment_Day!A7 -> Tuesday | B17: =Segment_Day!B7 -> 74572 | C17: =Segment_Day!D7 -> 2907 | D17: =B17/SUM($B$16:$B$22) -> 0.13208473 | E17: =C17/SUM($C$16:$C$22) -> 0.12357592 | F17: =(D17-E17)*100 -> 0.85088065 | G17: =(B17+C17)*SUM($B$16:$B$22)/(SUM($B$16:$B$22)+SUM($C$16:$C$22)) -> 74379.845 | H17: =(B17+C17)*SUM($C$16:$C$22)/(SUM($B$16:$B$22)+SUM($C$16:$C$22)) -> 3099.1547
A18: =Segment_Day!A8 -> Wednesday | B18: =Segment_Day!B8 -> 77418 | C18: =Segment_Day!D8 -> 3490 | D18: =B18/SUM($B$16:$B$22) -> 0.13712567 | E18: =C18/SUM($C$16:$C$22) -> 0.14835912 | F18: =(D18-E18)*100 -> -1.1233452 | G18: =(B18+C18)*SUM($B$16:$B$22)/(SUM($B$16:$B$22)+SUM($C$16:$C$22)) -> 77671.686 | H18: =(B18+C18)*SUM($C$16:$C$22)/(SUM($B$16:$B$22)+SUM($C$16:$C$22)) -> 3236.3145
A19: =Segment_Day!A9 -> Thursday | B19: =Segment_Day!B9 -> 79077 | C19: =Segment_Day!D9 -> 3905 | D19: =B19/SUM($B$16:$B$22) -> 0.14006415 | E19: =C19/SUM($C$16:$C$22) -> 0.16600068 | F19: =(D19-E19)*100 -> -2.5936526 | G19: =(B19+C19)*SUM($B$16:$B$22)/(SUM($B$16:$B$22)+SUM($C$16:$C$22)) -> 79662.726 | H19: =(B19+C19)*SUM($C$16:$C$22)/(SUM($B$16:$B$22)+SUM($C$16:$C$22)) -> 3319.2744
A20: =Segment_Day!A10 -> Friday | B20: =Segment_Day!B10 -> 88805 | C20: =Segment_Day!D10 -> 3803 | D20: =B20/SUM($B$16:$B$22) -> 0.15729475 | E20: =C20/SUM($C$16:$C$22) -> 0.16166468 | F20: =(D20-E20)*100 -> -0.43699295 | G20: =(B20+C20)*SUM($B$16:$B$22)/(SUM($B$16:$B$22)+SUM($C$16:$C$22)) -> 88903.686 | H20: =(B20+C20)*SUM($C$16:$C$22)/(SUM($B$16:$B$22)+SUM($C$16:$C$22)) -> 3704.3137
A21: =Segment_Day!A11 -> Saturday | B21: =Segment_Day!B11 -> 78802 | C21: =Segment_Day!D11 -> 2858 | D21: =B21/SUM($B$16:$B$22) -> 0.13957706 | E21: =C21/SUM($C$16:$C$22) -> 0.12149294 | F21: =(D21-E21)*100 -> 1.8084121 | G21: =(B21+C21)*SUM($B$16:$B$22)/(SUM($B$16:$B$22)+SUM($C$16:$C$22)) -> 78393.606 | H21: =(B21+C21)*SUM($C$16:$C$22)/(SUM($B$16:$B$22)+SUM($C$16:$C$22)) -> 3266.3944
A22: =Segment_Day!A12 -> Sunday | B22: =Segment_Day!B12 -> 82332 | C22: =Segment_Day!D12 -> 3059 | D22: =B22/SUM($B$16:$B$22) -> 0.14582953 | E22: =C22/SUM($C$16:$C$22) -> 0.13003741 | F22: =(D22-E22)*100 -> 1.5792124 | G22: =(B22+C22)*SUM($B$16:$B$22)/(SUM($B$16:$B$22)+SUM($C$16:$C$22)) -> 81975.366 | H22: =(B22+C22)*SUM($C$16:$C$22)/(SUM($B$16:$B$22)+SUM($C$16:$C$22)) -> 3415.6342
A23: Chi-square p-value | B23: =CHITEST(B16:C22,G16:H22) -> 4.8490677e-48 | C23: Max |share diff| (pp): | D23: =MAX(MAX(F16:F22),-MIN(F16:F22)) -> 2.5936526 | E23: =IF(B23<Inputs!$B$10,"Distribution differs (check size of gap)","No evidence of imbalance") -> Distribution differs (check size of gap)
A26: Average exposure
A27: Metric | B27: Ad | C27: PSA
A28: Mean ads per user | B28: =Inputs!B13 -> 24.8234 | C28: =Inputs!B14 -> 24.7611
A29: Median ads per user | B29: =Inputs!B15 -> 13 | C29: =Inputs!B16 -> 12
A31: Reading this: with ~588k users a chi-square test flags even small gaps, so judge the size of the gaps. Here some bands differ by several percentage points (see Max |share diff|), too large to dismiss. Because total_ads and most_ads_day are measured after the ad is served, a gap could be a delivery effect of the treatment or a sign that assignment was not purely random; the dataset cannot distinguish the two. The 96% / 4% split also cannot be checked against an intended allocation because the design is undocumented. Verify the assignment mechanism before treating the lift as causal.

Sheet Power_Planner
A1: Power planner and test cross-check
A2: Two statistical extensions, both pure Excel formulas: (A) an independent check of the headline z-test, (B) the sample size a follow-up experiment needs (supports next steps 3 and 4 in Decision_Memo).
A4: A. Cross-check: chi-square test of independence on the 2 x 2 table (group x converted)
A5: Group | B5: Converted | C5: Not converted | D5: Total | E5: Expected converted | F5: Expected not converted
A6: Ad (test) | B6: =Inputs!B5 -> 14423 | C6: =Inputs!B4-Inputs!B5 -> 550154 | D6: =B6+C6 -> 564577 | E6: =$D6*B$8/$D$8 -> 14249.281 | F6: =$D6*C$8/$D$8 -> 550327.72
A7: PSA (comparison) | B7: =Inputs!B7 -> 420 | C7: =Inputs!B6-Inputs!B7 -> 23104 | D7: =B7+C7 -> 23524 | E7: =$D7*B$8/$D$8 -> 593.71899 | F7: =$D7*C$8/$D$8 -> 22930.281
A8: Total | B8: =SUM(B6:B7) -> 14843 | C8: =SUM(C6:C7) -> 573258 | D8: =SUM(D6:D7) -> 588101
A10: Chi-square statistic | B10: =SUMPRODUCT((B6:C7-E6:F7)^2/E6:F7) -> 54.318052 | C10: Sum of (observed - expected)^2 / expected
A11: Degrees of freedom | B11: 1 | C11: (rows - 1) x (columns - 1) = 1
A12: Two-sided p-value | B12: =CHIDIST(B10,B11) -> 1.7052807e-13
A13: z statistic squared (Statistical_Test) | B13: =Statistical_Test!B11^2 -> 54.318052
A14: Difference (chi-square - z squared) | B14: =B10-B13 -> 0
A15: Agreement | B15: =IF(ABS(B14)<0.000001,"Chi-square equals z squared: both tests agree","Tests disagree: check inputs") -> Chi-square equals z squared: both tests agree
A17: B. Sample size for a follow-up test (two-proportion z-test, two-sided)
A18: Assumption / result | B18: Value | C18: Note
A19: Significance level (alpha) | B19: =Inputs!B10 -> 0.05 | C19: Linked to Inputs
A20: Target statistical power | B20: =Inputs!B12 -> 0.8 | C20: Linked to Inputs
A21: Baseline (control) conversion rate | B21: =Summary!C7 -> 0.017854106 | C21: Defaults to the observed PSA rate. Overwrite with your own baseline.
A22: Smallest absolute lift worth detecting | B22: 0.005 | C22: Placeholder (0.5 percentage points). Decide this from the break-even on Break_Even.
A23: Share of users in the control arm | B23: 0.5 | C23: Placeholder. The original test put about 4% in PSA.
A24: Critical z for alpha | B24: =NORMSINV(1-B19/2) -> 1.959964 | C24: NORMSINV(1 - alpha/2)
A25: z for power | B25: =NORMSINV(B20) -> 0.84162123 | C25: NORMSINV(power)
A26: Treatment conversion rate to detect | B26: =B21+B22 -> 0.022854106 | C26: Baseline + lift
A27: Allocation ratio k (treatment / control) | B27: =(1-B23)/B23 -> 1 | C27: k = 1 for an even split
A28: Control users needed | B28: =ROUNDUP((B24*SQRT((1+1/B27)*((B21+B27*B26)/(1+B27))*(1-(B21+B27*B26)/(1+B27)))+B25*SQRT(B21*(1-B21)+B26*(1-B26)/B27))^2/B22^2,0) -> 12520 | C28: Unequal-allocation formula; reduces to the standard one when k = 1
A29: Treatment users needed | B29: =ROUNDUP(B27*B28,0) -> 12520 | C29: k x control users
A30: Total users needed | B30: =B28+B29 -> 25040 | C30: Compare with the users in the original test, next row
A31: Users in the original experiment | B31: =Inputs!B4+Inputs!B6 -> 588101 | C31: Ad + PSA
A32: Users per arm to detect the observed lift (even split) | B32: =ROUNDUP(($B$24*SQRT(2*(B21+Summary!B8/2)*(1-B21-Summary!B8/2))+$B$25*SQRT(B21*(1-B21)+(B21+Summary!B8)*(1-B21-Summary!B8)))^2/Summary!B8^2,0) -> 5631 | C32: Replication sample: the observed 0.769 pp lift at the PSA baseline
A34: Users needed per arm (even split): rows = absolute lift to detect, columns = baseline conversion rate
A35: Lift \ Baseline | B35: 0.01 | C35: 0.02 | D35: 0.03 | E35: 0.05 | F35: 0.1
A36: 0.0025 | B36: =ROUNDUP(($B$24*SQRT(2*(B$35+$A36/2)*(1-B$35-$A36/2))+$B$25*SQRT(B$35*(1-B$35)+(B$35+$A36)*(1-B$35-$A36)))^2/$A36^2,0) -> 27937 | C36: =ROUNDUP(($B$24*SQRT(2*(C$35+$A36/2)*(1-C$35-$A36/2))+$B$25*SQRT(C$35*(1-C$35)+(C$35+$A36)*(1-C$35-$A36)))^2/$A36^2,0) -> 52238 | D36: =ROUNDUP(($B$24*SQRT(2*(D$35+$A36/2)*(1-D$35-$A36/2))+$B$25*SQRT(D$35*(1-D$35)+(D$35+$A36)*(1-D$35-$A36)))^2/$A36^2,0) -> 76035 | E36: =ROUNDUP(($B$24*SQRT(2*(E$35+$A36/2)*(1-E$35-$A36/2))+$B$25*SQRT(E$35*(1-E$35)+(E$35+$A36)*(1-E$35-$A36)))^2/$A36^2,0) -> 122124 | F36: =ROUNDUP(($B$24*SQRT(2*(F$35+$A36/2)*(1-F$35-$A36/2))+$B$25*SQRT(F$35*(1-F$35)+(F$35+$A36)*(1-F$35-$A36)))^2/$A36^2,0) -> 228555
A37: 0.005 | B37: =ROUNDUP(($B$24*SQRT(2*(B$35+$A37/2)*(1-B$35-$A37/2))+$B$25*SQRT(B$35*(1-B$35)+(B$35+$A37)*(1-B$35-$A37)))^2/$A37^2,0) -> 7750 | C37: =ROUNDUP(($B$24*SQRT(2*(C$35+$A37/2)*(1-C$35-$A37/2))+$B$25*SQRT(C$35*(1-C$35)+(C$35+$A37)*(1-C$35-$A37)))^2/$A37^2,0) -> 13809 | D37: =ROUNDUP(($B$24*SQRT(2*(D$35+$A37/2)*(1-D$35-$A37/2))+$B$25*SQRT(D$35*(1-D$35)+(D$35+$A37)*(1-D$35-$A37)))^2/$A37^2,0) -> 19743 | E37: =ROUNDUP(($B$24*SQRT(2*(E$35+$A37/2)*(1-E$35-$A37/2))+$B$25*SQRT(E$35*(1-E$35)+(E$35+$A37)*(1-E$35-$A37)))^2/$A37^2,0) -> 31234 | F37: =ROUNDUP(($B$24*SQRT(2*(F$35+$A37/2)*(1-F$35-$A37/2))+$B$25*SQRT(F$35*(1-F$35)+(F$35+$A37)*(1-F$35-$A37)))^2/$A37^2,0) -> 57763
A38: 0.0075 | B38: =ROUNDUP(($B$24*SQRT(2*(B$35+$A38/2)*(1-B$35-$A38/2))+$B$25*SQRT(B$35*(1-B$35)+(B$35+$A38)*(1-B$35-$A38)))^2/$A38^2,0) -> 3784 | C38: =ROUNDUP(($B$24*SQRT(2*(C$35+$A38/2)*(1-C$35-$A38/2))+$B$25*SQRT(C$35*(1-C$35)+(C$35+$A38)*(1-C$35-$A38)))^2/$A38^2,0) -> 6470 | D38: =ROUNDUP(($B$24*SQRT(2*(D$35+$A38/2)*(1-D$35-$A38/2))+$B$25*SQRT(D$35*(1-D$35)+(D$35+$A38)*(1-D$35-$A38)))^2/$A38^2,0) -> 9100 | E38: =ROUNDUP(($B$24*SQRT(2*(E$35+$A38/2)*(1-E$35-$A38/2))+$B$25*SQRT(E$35*(1-E$35)+(E$35+$A38)*(1-E$35-$A38)))^2/$A38^2,0) -> 14193 | F38: =ROUNDUP(($B$24*SQRT(2*(F$35+$A38/2)*(1-F$35-$A38/2))+$B$25*SQRT(F$35*(1-F$35)+(F$35+$A38)*(1-F$35-$A38)))^2/$A38^2,0) -> 25949
A39: 0.01 | B39: =ROUNDUP(($B$24*SQRT(2*(B$35+$A39/2)*(1-B$35-$A39/2))+$B$25*SQRT(B$35*(1-B$35)+(B$35+$A39)*(1-B$35-$A39)))^2/$A39^2,0) -> 2319 | C39: =ROUNDUP(($B$24*SQRT(2*(C$35+$A39/2)*(1-C$35-$A39/2))+$B$25*SQRT(C$35*(1-C$35)+(C$35+$A39)*(1-C$35-$A39)))^2/$A39^2,0) -> 3826 | D39: =ROUNDUP(($B$24*SQRT(2*(D$35+$A39/2)*(1-D$35-$A39/2))+$B$25*SQRT(D$35*(1-D$35)+(D$35+$A39)*(1-D$35-$A39)))^2/$A39^2,0) -> 5301 | E39: =ROUNDUP(($B$24*SQRT(2*(E$35+$A39/2)*(1-E$35-$A39/2))+$B$25*SQRT(E$35*(1-E$35)+(E$35+$A39)*(1-E$35-$A39)))^2/$A39^2,0) -> 8158 | F39: =ROUNDUP(($B$24*SQRT(2*(F$35+$A39/2)*(1-F$35-$A39/2))+$B$25*SQRT(F$35*(1-F$35)+(F$35+$A39)*(1-F$35-$A39)))^2/$A39^2,0) -> 14751
A40: 0.02 | B40: =ROUNDUP(($B$24*SQRT(2*(B$35+$A40/2)*(1-B$35-$A40/2))+$B$25*SQRT(B$35*(1-B$35)+(B$35+$A40)*(1-B$35-$A40)))^2/$A40^2,0) -> 769 | C40: =ROUNDUP(($B$24*SQRT(2*(C$35+$A40/2)*(1-C$35-$A40/2))+$B$25*SQRT(C$35*(1-C$35)+(C$35+$A40)*(1-C$35-$A40)))^2/$A40^2,0) -> 1141 | D40: =ROUNDUP(($B$24*SQRT(2*(D$35+$A40/2)*(1-D$35-$A40/2))+$B$25*SQRT(D$35*(1-D$35)+(D$35+$A40)*(1-D$35-$A40)))^2/$A40^2,0) -> 1506 | E40: =ROUNDUP(($B$24*SQRT(2*(E$35+$A40/2)*(1-E$35-$A40/2))+$B$25*SQRT(E$35*(1-E$35)+(E$35+$A40)*(1-E$35-$A40)))^2/$A40^2,0) -> 2213 | F40: =ROUNDUP(($B$24*SQRT(2*(F$35+$A40/2)*(1-F$35-$A40/2))+$B$25*SQRT(F$35*(1-F$35)+(F$35+$A40)*(1-F$35-$A40)))^2/$A40^2,0) -> 3841
A41: Reading the grid: halving the lift you want to detect roughly quadruples the users needed, and a lower baseline rate needs more users for the same absolute lift. Axis values (blue) can be edited.

Sheet Charts
A1: Charts
A2: Native Excel charts driven by the sheets above.

Sheet Decision_Memo
A1: Decision memo | ExperimentLab
A2: Numbers below are formulas and update with the Inputs sheet.
A4: Question | B4: Did the ad group convert at a different rate than the PSA comparison group, and is the improvement large enough to justify continued investment?
A5: Evidence | B5: ="Ad: "&TEXT(Inputs!B5,"#,##0")&" / "&TEXT(Inputs!B4,"#,##0")&" = "&TEXT(Summary!B7,"0.000%")&". PSA: "&TEXT(Inputs!B7,"#,##0")&" / "&TEXT(Inputs!B6,"#,##0")&" = "&TEXT(Summary!C7,"0.000%")&"." -> Ad: 14,423 / 564,577 = 2.555%. PSA: 420 / 23,524 = 1.785%.
A6: Effect size | B6: ="Absolute difference = "&TEXT(Summary!B8*100,"0.000")&" percentage points; relative lift = "&TEXT(Summary!B9,"0.0%")&" (95% CI "&TEXT(Statistical_Test!B19,"0%")&" to "&TEXT(Statistical_Test!B20,"0%")&"). Cohen's h = "&TEXT(Summary!B11,"0.000")&" (small in standardised terms; the conversion base rate is low)." -> Absolute difference = 0.769 percentage points; relative lift = 43.1% (95% CI 30% to 58%). Cohen's h = 0.053 (small in standardised terms; the conversion base rate is low).
A7: Uncertainty | B7: ="95% CI for the difference: "&TEXT(Statistical_Test!B15*100,"0.000")&" to "&TEXT(Statistical_Test!B16*100,"0.000")&" pp. The interval excludes zero, and its lower bound is still positive." -> 95% CI for the difference: 0.595 to 0.943 pp. The interval excludes zero, and its lower bound is still positive.
A8: Test | B8: ="Two-sided two-proportion z-test: z = "&TEXT(Statistical_Test!B11,"0.000")&", p = "&TEXT(Statistical_Test!B12,"0.00E+00")&". "&Statistical_Test!B21&"." -> Two-sided two-proportion z-test: z = 7.370, p = 1.71E-13. Statistically significant at 5%.
A9: Where the lift comes from | B9: ="The lift is not uniform. Below 21 ads there is no significant difference (PSA is nominally higher at 2-10 ads); users who saw 21+ ads account for "&TEXT(Segment_Frequency!B27,"0%")&" of band-level incremental conversions. Standardising for exposure band gives "&TEXT(Segment_Frequency!B20*100,"0.000")&" pp vs "&TEXT(Summary!B8*100,"0.000")&" pp crude, so exposure mix does not explain the lift away." -> The lift is not uniform. Below 21 ads there is no significant difference (PSA is nominally higher at 2-10 ads); users who saw 21+ ads account for 104% of band-level incremental conversions. Standardising for exposure band gives 0.819 pp vs 0.769 pp crude, so exposure mix does not explain the lift away.
A10: Business implication | B10: ="If the effect is causal, the ad produced about "&TEXT(Summary!B12,"#,##0")&" incremental conversions ("&TEXT(Summary!B13,"0%")&" of ad-group conversions). Break_Even shows the campaign pays back when each conversion is worth more than "&TEXT(Break_Even!B14,"$#,##0.00")&" at the assumed CPM of "&TEXT(Break_Even!B6,"$#,##0.00")&" (placeholder assumption)." -> If the effect is causal, the ad produced about 4,343 incremental conversions (30% of ad-group conversions). Break_Even shows the campaign pays back when each conversion is worth more than $16.13 at the assumed CPM of $5.00 (placeholder assumption).
A11: Recommendation | B11: The ad group converts at a meaningfully higher rate and the difference is statistically robust. Continue the campaign conditionally: (1) verify how users were assigned and what the PSA group saw (exposure profiles differ between groups), (2) replace the placeholder CPM and conversion value with real figures and confirm the break-even is cleared, (3) test frequency caps and targeting, because low-frequency exposure shows little benefit, (4) replicate before a large budget increase.
A12: ROI | B12: Cannot be determined from the dataset: no campaign spend, revenue per conversion, margin or lifetime value. Break_Even is a framework with placeholder inputs.
A13: Limitations | B13: ="Assignment process undocumented (association, not proven causation). The groups' exposure profiles differ by up to "&TEXT(Balance_Check!D12,"0.0")&" pp per ad-frequency band, which could reflect delivery differences or non-random assignment. PSA group is only 4% of users. Segments are defined after exposure and are exploratory (Bonferroni-adjusted p-values reported). Conversion window and campaign dates are not documented." -> Assignment process undocumented (association, not proven causation). The groups' exposure profiles differ by up to 4.2 pp per ad-frequency band, which could reflect delivery differences or non-random assignment. PSA group is only 4% of users. Segments are defined after exposure and are exploratory (Bonferroni-adjusted p-values reported). Conversion window and campaign dates are not documented.
A14: Next steps | B14: 1) Validate experiment design. 2) Add spend and value inputs. 3) Pre-register segment hypotheses. 4) Run a follow-up test with frequency-capped arms. Power_Planner shows the sample size the follow-up test needs.
